setup.py
vizit/Generalviz.py
vizit/Onedimension.py
vizit/Twodimension.py
vizit/__init__.py
vizit.egg-info/PKG-INFO
vizit.egg-info/SOURCES.txt
vizit.egg-info/dependency_links.txt
vizit.egg-info/not-zip-safe
vizit.egg-info/top_level.txt