Metadata-Version: 1.0
Name: vizit
Version: 0.1
Summary: Visualization tool built on top of Numpy, Pandas, Matplotlib, and Seaborn
Home-page: UNKNOWN
Author: UNKNOWN
Author-email: UNKNOWN
License: UNKNOWN
Platform: UNKNOWN
